[{"Word":"épatant","Checked":true,"Valid":false,"Msg":"Word doesn't exist"},{"Word":"épaulement","Checked":true,"Valid":false,"Msg":"Word doesn't exist"},{"Word":"épaulière","Checked":true,"Valid":false,"Msg":"Word doesn't exist"},{"Word":"épinal","Checked":true,"Valid":false,"Msg":"Word doesn't exist"},{"Word":"épinglé","Checked":true,"Valid":false,"Msg":"Word doesn't exist"},{"Word":"épée","Checked":true,"Valid":false,"Msg":"Word doesn't exist"},{"Word":"épéeist","Checked":true,"Valid":false,"Msg":"Word doesn't exist"},{"Word":"équipe","Checked":true,"Valid":false,"Msg":"Word doesn't exist"},{"Word":"étagère","Checked":true,"Valid":false,"Msg":"Word doesn't exist"},{"Word":"étape","Checked":true,"Valid":false,"Msg":"Word doesn't exist"},{"Word":"étienne","Checked":true,"Valid":false,"Msg":"Word doesn't exist"},{"Word":"éboulement","Checked":true,"Valid":false,"Msg":"Word doesn't exist"},{"Word":"écarté","Checked":true,"Valid":false,"Msg":"Word doesn't exist"},{"Word":"échappé","Checked":true,"Valid":false,"Msg":"Word doesn't exist"},{"Word":"échappée","Checked":true,"Valid":false,"Msg":"Word doesn't exist"},{"Word":"éclair","Checked":true,"Valid":false,"Msg":"Word doesn't exist"},{"Word":"éclaircissement","Checked":true,"Valid":false,"Msg":"Word doesn't exist"},{"Word":"éclat","Checked":true,"Valid":false,"Msg":"Word doesn't exist"},{"Word":"école","Checked":true,"Valid":false,"Msg":"Word doesn't exist"},{"Word":"écorché","Checked":true,"Valid":false,"Msg":"Word doesn't exist"},{"Word":"écossaise","Checked":true,"Valid":false,"Msg":"Word doesn't exist"},{"Word":"écraseur","Checked":true,"Valid":false,"Msg":"Word doesn't exist"},{"Word":"écrasé","Checked":true,"Valid":false,"Msg":"Word doesn't exist"},{"Word":"écrevisse","Checked":true,"Valid":false,"Msg":"Word doesn't exist"},{"Word":"écu","Checked":true,"Valid":false,"Msg":"Word doesn't exist"},{"Word":"écurie","Checked":true,"Valid":false,"Msg":"Word doesn't exist"},{"Word":"édhessa","Checked":true,"Valid":false,"Msg":"Word doesn't exist"},{"Word":"égalité","Checked":true,"Valid":false,"Msg":"Word doesn't exist"},{"Word":"élan","Checked":true,"Valid":false,"Msg":"Word doesn't exist"},{"Word":"élan vital","Checked":true,"Valid":false,"Msg":"Word doesn't exist"},{"Word":"émile","Checked":true,"Valid":false,"Msg":"Word doesn't exist"}]